doree/__init__.py
doree/code.py
doree/footPrinting.py
doree/hackWindows.py
doree/iptables.py
doree/macChanger.py
doree/passwordCrack.py
doree/phishing.py
doree-0.3.0.dist-info/METADATA
doree-0.3.0.dist-info/WHEEL
doree-0.3.0.dist-info/top_level.txt
doree-0.3.0.dist-info/RECORD
