Metadata-Version: 2.4
Name: doree
Version: 0.3.0
Summary: A sample Python package
Author-email: Capy Bara <capyslayers@gmail.com>
Requires-Dist: IPython
